apaupercary/__init__.py
apaupercary/cardkingdom.py
apaupercary/pipelines.py
apaupercary/scryfall.py
apaupercary/utils.py
apaupercary-0.0.6.dist-info/METADATA
apaupercary-0.0.6.dist-info/WHEEL
apaupercary-0.0.6.dist-info/top_level.txt
apaupercary-0.0.6.dist-info/RECORD
