Metadata-Version: 2.1
Name: apaupercary
Version: 0.0.6
Summary: pauper prices for your budget brews
Home-page: https://pypi.org/project/apaupercary/
Author: Sumner Magruder
Author-email: sumner.magruder@zmnh.uni-hamburg.de
License: UNKNOWN
Platform: UNKNOWN
Classifier: Programming Language :: Python :: 3.5
Classifier: License :: OSI Approved :: MIT License
Classifier: Operating System :: OS Independent
